{"version": "1.0", "paths": {"homepagestatic/fonts/fontawesome-webfont.eot?v=4.6.3": "homepagestatic/fonts/fontawesome-webfont.25a32416abee.eot?v=4.6.3", "homepagestatic/fonts/fontawesome-webfont.eot": "homepagestatic/fonts/fontawesome-webfont.25a32416abee.eot", "homepagestatic/fonts/fontawesome-webfont.woff2?v=4.6.3": "homepagestatic/fonts/fontawesome-webfont.e6cf7c6ec7c2.woff2?v=4.6.3", "homepagestatic/fonts/fontawesome-webfont.woff?v=4.6.3": "homepagestatic/fonts/fontawesome-webfont.c8ddf1e5e5bf.woff?v=4.6.3", "homepagestatic/fonts/fontawesome-webfont.ttf?v=4.6.3": "homepagestatic/fonts/fontawesome-webfont.1dc35d25e61d.ttf?v=4.6.3", "homepagestatic/fonts/fontawesome-webfont.svg?v=4.6.3": "homepagestatic/fonts/fontawesome-webfont.d7c639084f68.svg?v=4.6.3", "homepagestatic/images/bg.jpg": "homepagestatic/images/bg.31ba2a80ecea.jpg", "homepagestatic/images/overlay.png": "homepagestatic/images/overlay.5014f9cce435.png", "homepagestatic/images/bg1.jpg": "homepagestatic/images/bg1.90c271f642d8.jpg", "homepagestatic/images/move-up.png": "homepagestatic/images/move-up.93ecad676fb1.png", "homepagestatic/images/img3.jpg": "homepagestatic/images/img3.bc6e8b483c49.jpg", "mdb/font/roboto/Roboto-Thin.eot": "mdb/font/roboto/Roboto-Thin.dfe56a876d02.eot", "mdb/font/roboto/Roboto-Thind41d.eot": "mdb/font/roboto/Roboto-Thind41d.dfe56a876d02.eot", "mdb/font/roboto/Roboto-Thin.woff2": "mdb/font/roboto/Roboto-Thin.954bbdeb8648.woff2", "mdb/font/roboto/Roboto-Thin.woff": "mdb/font/roboto/Roboto-Thin.7500519de3d8.woff", "mdb/font/roboto/Roboto-Thin.ttf": "mdb/font/roboto/Roboto-Thin.94998475f6ae.ttf", "mdb/font/roboto/Roboto-Light.eot": "mdb/font/roboto/Roboto-Light.a990f611f230.eot", "mdb/font/roboto/Roboto-Lightd41d.eot": "mdb/font/roboto/Roboto-Lightd41d.a990f611f230.eot", "mdb/font/roboto/Roboto-Light.woff2": "mdb/font/roboto/Roboto-Light.69f8a0617ac4.woff2", "mdb/font/roboto/Roboto-Light.woff": "mdb/font/roboto/Roboto-Light.3b813c2ae0d0.woff", "mdb/font/roboto/Roboto-Light.ttf": "mdb/font/roboto/Roboto-Light.46e48ce06288.ttf", "mdb/font/roboto/Roboto-Regular.eot": "mdb/font/roboto/Roboto-Regular.30799efa5bf7.eot", "mdb/font/roboto/Roboto-Regulard41d.eot": "mdb/font/roboto/Roboto-Regulard41d.30799efa5bf7.eot", "mdb/font/roboto/Roboto-Regular.woff2": "mdb/font/roboto/Roboto-Regular.2751ee43015f.woff2", "mdb/font/roboto/Roboto-Regular.woff": "mdb/font/roboto/Roboto-Regular.ba3dcd8903e3.woff", "mdb/font/roboto/Roboto-Regular.ttf": "mdb/font/roboto/Roboto-Regular.df7b648ce535.ttf", "mdb/font/roboto/Roboto-Medium.eot": "mdb/font/roboto/Roboto-Medium.4d9f3f9e5195.eot", "mdb/font/roboto/Roboto-Mediumd41d.eot": "mdb/font/roboto/Roboto-Mediumd41d.4d9f3f9e5195.eot", "mdb/font/roboto/Roboto-Medium.woff2": "mdb/font/roboto/Roboto-Medium.574fd0b50367.woff2", "mdb/font/roboto/Roboto-Medium.woff": "mdb/font/roboto/Roboto-Medium.fc78759e93a6.woff", "mdb/font/roboto/Roboto-Medium.ttf": "mdb/font/roboto/Roboto-Medium.894a2ede85a4.ttf", "mdb/font/roboto/Roboto-Bold.eot": "mdb/font/roboto/Roboto-Bold.ecdd509cadbf.eot", "mdb/font/roboto/Roboto-Boldd41d.eot": "mdb/font/roboto/Roboto-Boldd41d.ecdd509cadbf.eot", "mdb/font/roboto/Roboto-Bold.woff2": "mdb/font/roboto/Roboto-Bold.39b2c3031be6.woff2", "mdb/font/roboto/Roboto-Bold.woff": "mdb/font/roboto/Roboto-Bold.dc81817def27.woff", "mdb/font/roboto/Roboto-Bold.ttf": "mdb/font/roboto/Roboto-Bold.e31fcf1885e3.ttf", "mdb/img/overlays/01.png": "mdb/img/overlays/01.0a3750e6fdb2.png", "mdb/img/overlays/02.png": "mdb/img/overlays/02.351bd6828f98.png", "mdb/img/overlays/03.png": "mdb/img/overlays/03.e438ea2aabdb.png", "mdb/img/overlays/04.png": "mdb/img/overlays/04.0284d042a6c2.png", "mdb/img/overlays/05.png": "mdb/img/overlays/05.5014f9cce435.png", "mdb/img/overlays/06.png": "mdb/img/overlays/06.21612b9d3e9d.png", "mdb/img/overlays/07.png": "mdb/img/overlays/07.f8da0281186d.png", "mdb/img/overlays/08.png": "mdb/img/overlays/08.975f7e007440.png", "mdb/img/overlays/09.png": "mdb/img/overlays/09.fd19309a1932.png", "mdb/img/svg/arrow_left.svg": "mdb/img/svg/arrow_left.11911410dca2.svg", "mdb/img/svg/arrow_right.svg": "mdb/img/svg/arrow_right.8ef6a08cdc11.svg", "ticketpagestatic/images/banner.jpg": "ticketpagestatic/images/banner.d0325e9383af.jpg", "admin/img/nav-bg.gif": "admin/img/nav-bg.5dadb8cd9865.gif", "admin/img/nav-bg-selected.gif": "admin/img/nav-bg-selected.4ebddc881b37.gif", "admin/img/nav-bg-reverse.gif": "admin/img/nav-bg-reverse.bd4701ff1aeb.gif", "admin/img/sorting-icons.gif": "admin/img/sorting-icons.2a27f8855e6b.gif", "admin/img/nav-bg-grabber.gif": "admin/img/nav-bg-grabber.45d7c744bbe8.gif", "admin/img/default-bg.gif": "admin/img/default-bg.af816e70c828.gif", "admin/img/default-bg-reverse.gif": "admin/img/default-bg-reverse.2c9949b0bac0.gif", "admin/img/icon_success.gif": "admin/img/icon_success.08e6b9d922e1.gif", "admin/img/icon_alert.gif": "admin/img/icon_alert.572a03fff47e.gif", "admin/img/icon_error.gif": "admin/img/icon_error.d0272cd88394.gif", "admin/img/icon_addlink.gif": "admin/img/icon_addlink.27872b1581c4.gif", "admin/img/icon_changelink.gif": "admin/img/icon_changelink.76183412227f.gif", "admin/img/icon_deletelink.gif": "admin/img/icon_deletelink.b797f0120322.gif", "admin/img/tooltag-arrowright.png": "admin/img/tooltag-arrowright.5aa2c86314d7.png", "admin/img/tooltag-add.png": "admin/img/tooltag-add.2152fd3b4a4d.png", "admin/img/changelist-bg.gif": "admin/img/changelist-bg.eaa563daae2a.gif", "admin/css/widgets.css": "admin/css/widgets.84396bf6dde3.css", "admin/img/selector-search.gif": "admin/img/selector-search.a5de786630be.gif", "admin/img/inline-delete-8bit.png": "admin/img/inline-delete-8bit.1c135ffae5f0.png", "admin/img/changelist-bg_rtl.gif": "admin/img/changelist-bg_rtl.db38ab536edc.gif", "admin/img/selector-icons.gif": "admin/img/selector-icons.4549da0d5c7f.gif", "admin/img/deleted-overlay.gif": "admin/img/deleted-overlay.1cd28ce73d7d.gif", "admin/img/inline-restore.png": "admin/img/inline-restore.a14579a2580f.png", "admin/img/inline-delete.png": "admin/img/inline-delete.4df86317f5c4.png", "admin/img/inline-splitter-bg.gif": "admin/img/inline-splitter-bg.3d67b08b4771.gif", "cdnjs.cloudflare.com\\ajax\\libs\\tether\\1.4.0\\js\\tether.min.js": "cdnjs.cloudflare.com\\ajax\\libs\\tether\\1.4.0\\js\\tether.min.ecdfd3dc464c.js", "mdb\\js\\vendor\\jvectormap\\jquery-jvectormap-2.0.3.css": "mdb/js/vendor/jvectormap/jquery-jvectormap-2.0.3.4ce7a71c6fa5.css", "mdb\\js\\vendor\\jvectormap\\jquery-jvectormap-2.0.3.min.js": "mdb\\js\\vendor\\jvectormap\\jquery-jvectormap-2.0.3.min.c57cf43ec38e.js", "mdb\\js\\vendor\\jvectormap\\jquery-jvectormap-world-mill.js": "mdb\\js\\vendor\\jvectormap\\jquery-jvectormap-world-mill.9b13fed64f6d.js", "mdb\\js\\vendor\\tinymce\\tinymce.min.js": "mdb\\js\\vendor\\tinymce\\tinymce.min.945b642ebfb7.js", "assets\\js\\vendor\\jquery.min.html": "assets\\js\\vendor\\jquery.min.baeb004575d5.html", "mdb\\font\\roboto\\Roboto-Bold.eot": "mdb\\font\\roboto\\Roboto-Bold.ecdd509cadbf.eot", "mdb\\font\\roboto\\Roboto-Bold.ttf": "mdb\\font\\roboto\\Roboto-Bold.e31fcf1885e3.ttf", "mdb\\font\\roboto\\Roboto-Bold.woff": "mdb\\font\\roboto\\Roboto-Bold.dc81817def27.woff", "mdb\\font\\roboto\\Roboto-Bold.woff2": "mdb\\font\\roboto\\Roboto-Bold.39b2c3031be6.woff2", "mdb\\font\\roboto\\Roboto-Boldd41d.eot": "mdb\\font\\roboto\\Roboto-Boldd41d.ecdd509cadbf.eot", "mdb\\font\\roboto\\Roboto-Light.eot": "mdb\\font\\roboto\\Roboto-Light.a990f611f230.eot", "mdb\\font\\roboto\\Roboto-Light.ttf": "mdb\\font\\roboto\\Roboto-Light.46e48ce06288.ttf", "mdb\\font\\roboto\\Roboto-Light.woff": "mdb\\font\\roboto\\Roboto-Light.3b813c2ae0d0.woff", "mdb\\font\\roboto\\Roboto-Light.woff2": "mdb\\font\\roboto\\Roboto-Light.69f8a0617ac4.woff2", "mdb\\font\\roboto\\Roboto-Lightd41d.eot": "mdb\\font\\roboto\\Roboto-Lightd41d.a990f611f230.eot", "mdb\\font\\roboto\\Roboto-Medium.eot": "mdb\\font\\roboto\\Roboto-Medium.4d9f3f9e5195.eot", "mdb\\font\\roboto\\Roboto-Medium.ttf": "mdb\\font\\roboto\\Roboto-Medium.894a2ede85a4.ttf", "mdb\\font\\roboto\\Roboto-Medium.woff": "mdb\\font\\roboto\\Roboto-Medium.fc78759e93a6.woff", "mdb\\font\\roboto\\Roboto-Medium.woff2": "mdb\\font\\roboto\\Roboto-Medium.574fd0b50367.woff2", "mdb\\font\\roboto\\Roboto-Mediumd41d.eot": "mdb\\font\\roboto\\Roboto-Mediumd41d.4d9f3f9e5195.eot", "mdb\\font\\roboto\\Roboto-Regular.eot": "mdb\\font\\roboto\\Roboto-Regular.30799efa5bf7.eot", "mdb\\font\\roboto\\Roboto-Regular.ttf": "mdb\\font\\roboto\\Roboto-Regular.df7b648ce535.ttf", "mdb\\font\\roboto\\Roboto-Regular.woff": "mdb\\font\\roboto\\Roboto-Regular.ba3dcd8903e3.woff", "mdb\\font\\roboto\\Roboto-Regular.woff2": "mdb\\font\\roboto\\Roboto-Regular.2751ee43015f.woff2", "mdb\\font\\roboto\\Roboto-Regulard41d.eot": "mdb\\font\\roboto\\Roboto-Regulard41d.30799efa5bf7.eot", "mdb\\font\\roboto\\Roboto-Thin.eot": "mdb\\font\\roboto\\Roboto-Thin.dfe56a876d02.eot", "mdb\\font\\roboto\\Roboto-Thin.ttf": "mdb\\font\\roboto\\Roboto-Thin.94998475f6ae.ttf", "mdb\\font\\roboto\\Roboto-Thin.woff": "mdb\\font\\roboto\\Roboto-Thin.7500519de3d8.woff", "mdb\\font\\roboto\\Roboto-Thin.woff2": "mdb\\font\\roboto\\Roboto-Thin.954bbdeb8648.woff2", "mdb\\font\\roboto\\Roboto-Thind41d.eot": "mdb\\font\\roboto\\Roboto-Thind41d.dfe56a876d02.eot", "mdb\\img\\flags\\cn.png": "mdb\\img\\flags\\cn.3f8fb102f474.png", "mdb\\img\\flags\\in.png": "mdb\\img\\flags\\in.0bce589c49b6.png", "mdb\\img\\flags\\it.png": "mdb\\img\\flags\\it.7afb68f6f985.png", "mdb\\img\\flags\\pl.png": "mdb\\img\\flags\\pl.5aaa71cf4f75.png", "mdb\\img\\flags\\us.png": "mdb\\img\\flags\\us.2556bc191786.png", "mdb\\img\\overlays\\01.png": "mdb\\img\\overlays\\01.0a3750e6fdb2.png", "mdb\\img\\overlays\\02.png": "mdb\\img\\overlays\\02.351bd6828f98.png", "mdb\\img\\overlays\\03.png": "mdb\\img\\overlays\\03.e438ea2aabdb.png", "mdb\\img\\overlays\\04.png": "mdb\\img\\overlays\\04.0284d042a6c2.png", "mdb\\img\\overlays\\05.png": "mdb\\img\\overlays\\05.5014f9cce435.png", "mdb\\img\\overlays\\06.png": "mdb\\img\\overlays\\06.21612b9d3e9d.png", "mdb\\img\\overlays\\07.png": "mdb\\img\\overlays\\07.f8da0281186d.png", "mdb\\img\\overlays\\08.png": "mdb\\img\\overlays\\08.975f7e007440.png", "mdb\\img\\overlays\\09.png": "mdb\\img\\overlays\\09.fd19309a1932.png", "mdb\\img\\overlays\\Thumbs.db": "mdb\\img\\overlays\\Thumbs.1f33b80d3350.db", "mdb\\img\\svg\\arrow_left.svg": "mdb\\img\\svg\\arrow_left.11911410dca2.svg", "mdb\\img\\svg\\arrow_right.svg": "mdb\\img\\svg\\arrow_right.8ef6a08cdc11.svg", "admin\\img\\gis\\move_vertex_off.png": "admin\\img\\gis\\move_vertex_off.93ee41d8cad9.png", "admin\\img\\gis\\move_vertex_on.png": "admin\\img\\gis\\move_vertex_on.99be2571b3f6.png", "admin\\js\\admin\\DateTimeShortcuts.js": "admin\\js\\admin\\DateTimeShortcuts.140919a6a17e.js", "admin\\js\\admin\\RelatedObjectLookups.js": "admin\\js\\admin\\RelatedObjectLookups.58b2336c1e19.js", "assets\\js\\ie10-viewport-bug-workaround.js": "assets\\js\\ie10-viewport-bug-workaround.56e8a7b02824.js", "dist\\css\\bootstrap.min.css": "dist/css/bootstrap.min.7e923ad223e9.css", "dist\\js\\bootstrap.min.js": "dist\\js\\bootstrap.min.0827a0bdcd9a.js", "examples\\dashboard\\dashboard.css": "examples/dashboard/dashboard.6c7fc2f40041.css", "examples\\dashboard\\index.html": "examples\\dashboard\\index.3207ee571404.html", "homepagestatic\\css\\bootstrap.css": "homepagestatic/css/bootstrap.4570e1183656.css", "homepagestatic\\css\\bootstrap.min.css": "homepagestatic/css/bootstrap.min.27e47d7bdb03.css", "homepagestatic\\css\\flexslider.css": "homepagestatic/css/flexslider.01b054079403.css", "homepagestatic\\css\\font-awesome.css": "homepagestatic/css/font-awesome.a16730221cf9.css", "homepagestatic\\css\\simplelightbox.min.css": "homepagestatic/css/simplelightbox.min.3353bcaa7bac.css", "homepagestatic\\css\\style.css": "homepagestatic/css/style.9f388c331566.css", "homepagestatic\\fonts\\fontawesome-webfont.eot": "homepagestatic/fonts/fontawesome-webfont.25a32416abee.eot", "homepagestatic\\fonts\\fontawesome-webfont.svg": "homepagestatic/fonts/fontawesome-webfont.d7c639084f68.svg", "homepagestatic\\fonts\\fontawesome-webfont.ttf": "homepagestatic/fonts/fontawesome-webfont.1dc35d25e61d.ttf", "homepagestatic\\fonts\\fontawesome-webfont.woff": "homepagestatic/fonts/fontawesome-webfont.c8ddf1e5e5bf.woff", "homepagestatic\\fonts\\fontawesome-webfont.woff2": "homepagestatic/fonts/fontawesome-webfont.e6cf7c6ec7c2.woff2", "homepagestatic\\fonts\\FontAwesome.otf": "homepagestatic/fonts/FontAwesome.5dc41d8fe329.otf", "homepagestatic\\fonts\\glyphicons-halflings-regular.woff": "homepagestatic/fonts/glyphicons-halflings-regular.fa2772327f55.woff", "homepagestatic\\fonts\\glyphicons-halflings-regular.woff2": "homepagestatic/fonts/glyphicons-halflings-regular.448c34a56d69.woff2", "homepagestatic\\images\\bg.jpg": "homepagestatic/images/bg.31ba2a80ecea.jpg", "homepagestatic\\images\\bg1.jpg": "homepagestatic/images/bg1.90c271f642d8.jpg", "homepagestatic\\images\\g1.jpg": "homepagestatic/images/g1.05b7de06bb34.jpg", "homepagestatic\\images\\g2.jpg": "homepagestatic/images/g2.96baab1c0584.jpg", "homepagestatic\\images\\g3.jpg": "homepagestatic/images/g3.a09eba690354.jpg", "homepagestatic\\images\\g4.jpg": "homepagestatic/images/g4.24b5aecc8f01.jpg", "homepagestatic\\images\\img1.jpg": "homepagestatic/images/img1.c7c9e9ab9d02.jpg", "homepagestatic\\images\\img2.jpg": "homepagestatic/images/img2.91be2d9fc67e.jpg", "homepagestatic\\images\\img3.jpg": "homepagestatic/images/img3.bc6e8b483c49.jpg", "homepagestatic\\images\\img4.jpg": "homepagestatic/images/img4.668cb58ef64c.jpg", "homepagestatic\\images\\img5.png": "homepagestatic/images/img5.4fae40d4be25.png", "homepagestatic\\images\\move-up.png": "homepagestatic/images/move-up.93ecad676fb1.png", "homepagestatic\\images\\overlay.png": "homepagestatic/images/overlay.5014f9cce435.png", "homepagestatic\\images\\t1.jpg": "homepagestatic/images/t1.cfba03b56ec6.jpg", "homepagestatic\\images\\t2.jpg": "homepagestatic/images/t2.f71f2a8dd15d.jpg", "homepagestatic\\images\\t3.jpg": "homepagestatic/images/t3.50b78f15c127.jpg", "homepagestatic\\images\\t4.jpg": "homepagestatic/images/t4.26c4579f82e8.jpg", "homepagestatic\\images\\t5.jpg": "homepagestatic/images/t5.9eb54afc5770.jpg", "homepagestatic\\images\\t6.jpg": "homepagestatic/images/t6.0666cb408ad8.jpg", "homepagestatic\\images\\t7.jpg": "homepagestatic/images/t7.556dddda70fc.jpg", "homepagestatic\\js\\bootstrap.js": "homepagestatic/js/bootstrap.9cb0532955cf.js", "homepagestatic\\js\\bootstrap.min.js": "homepagestatic/js/bootstrap.min.ba847811448e.js", "homepagestatic\\js\\easing.js": "homepagestatic/js/easing.6ee8b009ab1e.js", "homepagestatic\\js\\jarallax.js": "homepagestatic/js/jarallax.43e1988d13be.js", "homepagestatic\\js\\jquery-2.2.3.min.js": "homepagestatic/js/jquery-2.2.3.min.33cabfa15c10.js", "homepagestatic\\js\\jquery.flexslider.js": "homepagestatic/js/jquery.flexslider.c3b22bb22693.js", "homepagestatic\\js\\jquery.form.js": "homepagestatic/js/jquery.form.08a24670beb2.js", "homepagestatic\\js\\jquery.min.js": "homepagestatic/js/jquery.min.d021c983bd6e.js", "homepagestatic\\js\\login.js": "homepagestatic/js/login.9f9e78b49cbc.js", "homepagestatic\\js\\move-top.js": "homepagestatic/js/move-top.0ca97ca5c844.js", "homepagestatic\\js\\numscroller-1.0.js": "homepagestatic/js/numscroller-1.0.2fba96fbe453.js", "homepagestatic\\js\\simple-lightbox.min.js": "homepagestatic/js/simple-lightbox.min.9b12ff377401.js", "homepagestatic\\js\\SmoothScroll.min.js": "homepagestatic/js/SmoothScroll.min.a8d6bbcb4f03.js", "mdb\\css\\bootstrap.min.css": "mdb/css/bootstrap.min.1352ea40444e.css", "mdb\\css\\customizer.min.css": "mdb/css/customizer.min.68e2186d80f0.css", "mdb\\css\\font-awesome.min.css": "mdb/css/font-awesome.min.3c65cd1d610c.css", "mdb\\css\\mdb.css": "mdb/css/mdb.46000b55825d.css", "mdb\\css\\style.css": "mdb/css/style.0d68843c145a.css", "mdb\\js\\bootstrap.min.js": "mdb/js/bootstrap.min.9cd03defdd30.js", "mdb\\js\\customizer.min.js": "mdb/js/customizer.min.c35e8ba9a90f.js", "mdb\\js\\jquery-3.1.1.min.js": "mdb/js/jquery-3.1.1.min.5b5a269bd363.js", "mdb\\js\\mdb.js": "mdb/js/mdb.ee33c8f38e1d.js", "mdb\\js\\mdb.min.js": "mdb/js/mdb.min.375b542cd36a.js", "mdb\\js\\tether.min.js": "mdb/js/tether.min.dbdaedc86c54.js", "ticketpagestatic\\css\\jquery.seat-charts.css": "ticketpagestatic/css/jquery.seat-charts.69f8ef3a491d.css", "ticketpagestatic\\css\\style.css": "ticketpagestatic/css/style.982364a2f5b0.css", "ticketpagestatic\\images\\banner.jpg": "ticketpagestatic/images/banner.d0325e9383af.jpg", "ticketpagestatic\\js\\jquery-1.11.0.min.js": "ticketpagestatic/js/jquery-1.11.0.min.8fc25e27d427.js", "ticketpagestatic\\js\\jquery.nicescroll.js": "ticketpagestatic/js/jquery.nicescroll.c9844213bc1d.js", "ticketpagestatic\\js\\jquery.seat-charts.js": "ticketpagestatic/js/jquery.seat-charts.52f854f30b10.js", "ticketpagestatic\\js\\scripts.js": "ticketpagestatic/js/scripts.a4c30b37a6b0.js", "admin\\css\\base.css": "admin/css/base.f0d165989b77.css", "admin\\css\\changelists.css": "admin/css/changelists.facd9faec460.css", "admin\\css\\dashboard.css": "admin/css/dashboard.4898e2e9983d.css", "admin\\css\\forms.css": "admin/css/forms.812a4441d477.css", "admin\\css\\ie.css": "admin/css/ie.2ca52592ccf6.css", "admin\\css\\login.css": "admin/css/login.9ee3563a2bfe.css", "admin\\css\\rtl.css": "admin/css/rtl.b619957e18c9.css", "admin\\css\\widgets.css": "admin/css/widgets.84396bf6dde3.css", "admin\\img\\changelist-bg.gif": "admin/img/changelist-bg.eaa563daae2a.gif", "admin\\img\\changelist-bg_rtl.gif": "admin/img/changelist-bg_rtl.db38ab536edc.gif", "admin\\img\\default-bg-reverse.gif": "admin/img/default-bg-reverse.2c9949b0bac0.gif", "admin\\img\\default-bg.gif": "admin/img/default-bg.af816e70c828.gif", "admin\\img\\deleted-overlay.gif": "admin/img/deleted-overlay.1cd28ce73d7d.gif", "admin\\img\\icon-no.gif": "admin/img/icon-no.2888642640a3.gif", "admin\\img\\icon-unknown.gif": "admin/img/icon-unknown.662022bb6ab0.gif", "admin\\img\\icon-yes.gif": "admin/img/icon-yes.0596085e212f.gif", "admin\\img\\icon_addlink.gif": "admin/img/icon_addlink.27872b1581c4.gif", "admin\\img\\icon_alert.gif": "admin/img/icon_alert.572a03fff47e.gif", "admin\\img\\icon_calendar.gif": "admin/img/icon_calendar.b4704fc81e9d.gif", "admin\\img\\icon_changelink.gif": "admin/img/icon_changelink.76183412227f.gif", "admin\\img\\icon_clock.gif": "admin/img/icon_clock.d65ba15015dd.gif", "admin\\img\\icon_deletelink.gif": "admin/img/icon_deletelink.b797f0120322.gif", "admin\\img\\icon_error.gif": "admin/img/icon_error.d0272cd88394.gif", "admin\\img\\icon_searchbox.png": "admin/img/icon_searchbox.46952c2c6973.png", "admin\\img\\icon_success.gif": "admin/img/icon_success.08e6b9d922e1.gif", "admin\\img\\inline-delete-8bit.png": "admin/img/inline-delete-8bit.1c135ffae5f0.png", "admin\\img\\inline-delete.png": "admin/img/inline-delete.4df86317f5c4.png", "admin\\img\\inline-restore-8bit.png": "admin/img/inline-restore-8bit.19cd843fa6f9.png", "admin\\img\\inline-restore.png": "admin/img/inline-restore.a14579a2580f.png", "admin\\img\\inline-splitter-bg.gif": "admin/img/inline-splitter-bg.3d67b08b4771.gif", "admin\\img\\nav-bg-grabber.gif": "admin/img/nav-bg-grabber.45d7c744bbe8.gif", "admin\\img\\nav-bg-reverse.gif": "admin/img/nav-bg-reverse.bd4701ff1aeb.gif", "admin\\img\\nav-bg-selected.gif": "admin/img/nav-bg-selected.4ebddc881b37.gif", "admin\\img\\nav-bg.gif": "admin/img/nav-bg.5dadb8cd9865.gif", "admin\\img\\selector-icons.gif": "admin/img/selector-icons.4549da0d5c7f.gif", "admin\\img\\selector-search.gif": "admin/img/selector-search.a5de786630be.gif", "admin\\img\\sorting-icons.gif": "admin/img/sorting-icons.2a27f8855e6b.gif", "admin\\img\\tooltag-add.png": "admin/img/tooltag-add.2152fd3b4a4d.png", "admin\\img\\tooltag-arrowright.png": "admin/img/tooltag-arrowright.5aa2c86314d7.png", "admin\\js\\actions.js": "admin/js/actions.42b74ac13f07.js", "admin\\js\\actions.min.js": "admin/js/actions.min.2893760b9e40.js", "admin\\js\\calendar.js": "admin/js/calendar.df720acbe7bb.js", "admin\\js\\collapse.js": "admin/js/collapse.c781bafaf192.js", "admin\\js\\collapse.min.js": "admin/js/collapse.min.bf4e82bb444b.js", "admin\\js\\core.js": "admin/js/core.78280057239a.js", "admin\\js\\inlines.js": "admin/js/inlines.ec5c4bfbf84d.js", "admin\\js\\inlines.min.js": "admin/js/inlines.min.e3cd9638369f.js", "admin\\js\\jquery.init.js": "admin/js/jquery.init.575b5609d57c.js", "admin\\js\\jquery.js": "admin/js/jquery.c0b3962f9f23.js", "admin\\js\\jquery.min.js": "admin/js/jquery.min.5790ead7ad3b.js", "admin\\js\\LICENSE-JQUERY.txt": "admin/js/LICENSE-JQUERY.3c2025538601.txt", "admin\\js\\prepopulate.js": "admin/js/prepopulate.cd237b18d36c.js", "admin\\js\\prepopulate.min.js": "admin/js/prepopulate.min.4479f53b704f.js", "admin\\js\\related-widget-wrapper.js": "admin/js/related-widget-wrapper.3641d148e433.js", "admin\\js\\SelectBox.js": "admin/js/SelectBox.df843afcc450.js", "admin\\js\\SelectFilter2.js": "admin/js/SelectFilter2.54a4515a9134.js", "admin\\js\\timeparse.js": "admin/js/timeparse.a298a7ede5c3.js", "admin\\js\\urlify.js": "admin/js/urlify.687bc28c85b7.js", "code.jquery.com\\jquery-3.1.1.slim.min.js": "code.jquery.com/jquery-3.1.1.slim.min.550ddfe84a11.js", "import_export\\action_formats.js": "import_export/action_formats.e9f7d2c30a48.js", "dashboard.css": "dashboard.6c7fc2f40041.css"}}